programmer/__init__.py
programmer/agent.py
programmer/agent_texteditor.py
programmer/agent_texteditor_o1.py
programmer/config.py
programmer/console.py
programmer/environment.py
programmer/evaluate.py
programmer/file_protocol.py
programmer/git.py
programmer/io_context.py
programmer/programmer.py
programmer/settings_manager.py
programmer/text_editor.py
programmer/tool_calling.py
programmer/tools.py
programmer/containerserver/checkserver.py
programmer/containerserver/cmserver.py
programmer/evals/eval_repeated_edits.py
programmer/swebench/__init__.py
programmer/swebench/evaluate.py
programmer/swebench/run_instance.py
programmer/swebench/score.py
programmer/swebench/swebench_model.py
programmer/swebench/ingest/ingest_eval.py
programmer/swebench/ingest/make_dataset.py
programmer/swebench/scripts/example_v_models.py
programmer/swebench/scripts/verified_difficulty_labels.py
programmer/tests/conftest.py
programmer/tests/test_file_line_tools.py
programmer/tests/test_git_integration.py
programmer/tests/test_settings_manager.py
programmer/tests/test_text_editor.py
programmer/tests/test_tool_calling.py
programmer/tests/test_weave_query.py
programmer/weave_next/api.py
programmer/weave_next/weave_query.py
programmer-ui/ui.py
programmer-0.1.9.dist-info/LICENSE
programmer-0.1.9.dist-info/METADATA
programmer-0.1.9.dist-info/WHEEL
programmer-0.1.9.dist-info/entry_points.txt
programmer-0.1.9.dist-info/top_level.txt
programmer-0.1.9.dist-info/RECORD
