Metadata-Version: 2.1
Name: programmer
Version: 0.1.9
Summary: A Python package for managing programming tasks.
Author-email: Shawn Lewis <shawn@wandb.com>
License: Apache-2.0
Project-URL: Homepage, https://github.com/wandb/programmer
Requires-Python: >=3.10
License-File: LICENSE
Requires-Dist: weave>=0.51.1
Requires-Dist: streamlit
Requires-Dist: pandas
Requires-Dist: litellm
